[
    {
        "url": "https://www.sspc.co.uk/White-Lodge-Carberry-East-Lothian-EH21-8PZ-5-Bedroom-Detached-Bungalow-ESPC",
        "address": "White Lodge, Carberry, East Lothian EH21 8PZ",
        "priceDescription": "Offers over £860,000",
        "summary": "Detached Bungalow",
        "bedrooms": 5,
        "id": "fe4a5b19c3e1b1de6ff3c18d09656d05"
    },
    {
        "url": "https://www.sspc.co.uk/66-Buchanan-Gardens-ST.-ANDREWS-KY16-9LX-3-Bedroom-Detached-Bungalow-ESPC",
        "address": "66 Buchanan Gardens, ST. ANDREWS KY16 9LX",
        "priceDescription": "Offers over £785,000",
        "summary": "Detached Bungalow",
        "bedrooms": 3,
        "id": "3b57118e1e952468efa00b53d564c4b2"
    },
    {
        "url": "https://www.sspc.co.uk/72-Kaimes-Road-EDINBURGH-EH12-6LW-5-Bedroom-Detached-Bungalow-ESPC",
        "address": "72 Kaimes Road, EDINBURGH EH12 6LW",
        "priceDescription": "Offers over £645,000",
        "summary": "Detached Bungalow",
        "bedrooms": 5,
        "id": "abdaa3c9049097b6b0ad0d8d74e91859"
    },
    {
        "url": "https://www.sspc.co.uk/21-Braid-Hills-Avenue-EDINBURGH-EH10-6LH-5-Bedroom-Detached-Bungalow-ESPC",
        "address": "21 Braid Hills Avenue, EDINBURGH EH10 6LH",
        "priceDescription": "Offers over £640,000",
        "summary": "Detached Bungalow",
        "bedrooms": 5,
        "id": "47bc124022dc9d15472dffa5e7c3dcf8"
    },
    {
        "url": "https://www.sspc.co.uk/Linden-House-Linden-Park-TD9-8SU-4-Bedroom-Detached-Bungalow-BSPC",
        "address": "Linden House, Linden Park TD9 8SU",
        "priceDescription": "In the Region Of £610,000",
        "summary": "Detached Bungalow",
        "bedrooms": 4,
        "id": "fb3d9e88f042d07a1d42c15263319cad"
    },
    {
        "url": "https://www.sspc.co.uk/608-Queensferry-Road-Edinburgh-EH4-6AT-4-Bedroom-Detached-Bungalow-ESPC",
        "address": "608 Queensferry Road, Edinburgh EH4 6AT",
        "priceDescription": "Fixed Price £610,000",
        "summary": "Detached Bungalow",
        "bedrooms": 4,
        "id": "59c43fddbaa872956fb3127594a13529"
    },
    {
        "url": "https://www.sspc.co.uk/19-Pentland-Gardens-Edinburgh-EH10-6NN-3-Bedroom-Detached-Bungalow-ESPC",
        "address": "19 Pentland Gardens, Edinburgh EH10 6NN",
        "priceDescription": "Fixed Price £590,000",
        "summary": "Detached Bungalow",
        "bedrooms": 3,
        "id": "b2d1a53f2af2cab7fffa974d24396cb4"
    },
    {
        "url": "https://www.sspc.co.uk/26-Campbell-Road-Longniddry-East-Lothian-EH32-0NP-4-Bedroom-Detached-Bungalow-ESPC",
        "address": "26 Campbell Road, Longniddry, East Lothian EH32 0NP",
        "priceDescription": "Offers over £575,000",
        "summary": "Detached Bungalow",
        "bedrooms": 4,
        "id": "bfed123795a8a51ccd6e230d7ebfcd94"
    },
    {
        "url": "https://www.sspc.co.uk/16-Cramond-Park-Cramond-EH4-6PR-4-Bedroom-Detached-Bungalow-ESPC",
        "address": "16 Cramond Park, Cramond EH4 6PR",
        "priceDescription": "Fixed Price £545,000",
        "summary": "Detached Bungalow",
        "bedrooms": 4,
        "id": "d567a537aff46933634e10f52cc58902"
    },
    {
        "url": "https://www.sspc.co.uk/Strathearn-Ormiston-Terrace-TD6-9SW-4-Bedroom-Detached-Bungalow-BSPC",
        "address": "Strathearn, Ormiston Terrace TD6 9SW",
        "priceDescription": "Guide Price £525,000",
        "summary": "Detached Bungalow",
        "bedrooms": 4,
        "id": "b638b37461e2532621a2e936a730c4e0"
    },
    {
        "url": "https://www.sspc.co.uk/35-Ravelrig-Park-Balerno-EH14-7DL-4-Bedroom-Detached-Bungalow-ESPC",
        "address": "35 Ravelrig Park, Balerno EH14 7DL",
        "priceDescription": "Offers over £525,000",
        "summary": "Detached Bungalow",
        "bedrooms": 4,
        "id": "175a3c6ac473c9c4041c90ecf303bba6"
    },
    {
        "url": "https://www.sspc.co.uk/91-Milton-Road-West-EDINBURGH-EH15-1RA-3-Bedroom-Detached-Bungalow-ESPC",
        "address": "91 Milton Road West, EDINBURGH EH15 1RA",
        "priceDescription": "Fixed Price £520,000",
        "summary": "Detached Bungalow",
        "bedrooms": 3,
        "id": "27bd8f76795f99302c9c311e91d2e02b"
    },
    {
        "url": "https://www.sspc.co.uk/7-Corstorphine-Hill-Gardens-Edinburgh-EH12-6LB-4-Bedroom-Semi-Detached-Bungalow-ESPC",
        "address": "7 Corstorphine Hill Gardens, Edinburgh EH12 6LB",
        "priceDescription": "Fixed Price £520,000",
        "summary": "Semi-Detached Bungalow",
        "bedrooms": 4,
        "id": "a135a8b59484922af736e99302caea16"
    },
    {
        "url": "https://www.sspc.co.uk/10-Coillesdene-Drive-Joppa-Edinburgh-EH15-2JD-3-Bedroom-Detached-Bungalow-ESPC",
        "address": "10 Coillesdene Drive, Joppa, Edinburgh EH15 2JD",
        "priceDescription": "Offers over £515,000",
        "summary": "Detached Bungalow",
        "bedrooms": 3,
        "id": "417d0ffc306ae4c4406a8f71b95b1b17"
    },
    {
        "url": "https://www.sspc.co.uk/12-St-Bryde's-Way-Cardrona-Peebles-EH45-9LL-3-Bedroom-Detached-Bungalow-ESPC",
        "address": "12 St Bryde's Way, Cardrona, Peebles EH45 9LL",
        "priceDescription": "Offers over £510,000",
        "summary": "Detached Bungalow",
        "bedrooms": 3,
        "id": "68d144af9aa83d23c2760bd1687ac8de"
    },
    {
        "url": "https://www.sspc.co.uk/24-The-Wisp-Edinburgh-EH16-4SQ-3-Bedroom-Detached-Bungalow-ESPC",
        "address": "24 The Wisp, Edinburgh EH16 4SQ",
        "priceDescription": "Offers over £500,000",
        "summary": "Detached Bungalow",
        "bedrooms": 3,
        "id": "965f871c4ee9b6c82a1d2f61e30af076"
    },
    {
        "url": "https://www.sspc.co.uk/3-Jim-Hensman-Place-Saline-DUNFERMLINE-KY12-9GF-3-Bedroom-Detached-Bungalow-ESPC",
        "address": "3 Jim Hensman Place, Saline, DUNFERMLINE KY12 9GF",
        "priceDescription": "Offers over £499,950",
        "summary": "Detached Bungalow",
        "bedrooms": 3,
        "id": "558f18ab8f86cbd580935198c55b8f4e"
    },
    {
        "url": "https://www.sspc.co.uk/8-Livingstone-Crescent-ST.-ANDREWS-KY16-8JL-3-Bedroom-Detached-Bungalow-ESPC",
        "address": "8 Livingstone Crescent, ST. ANDREWS KY16 8JL",
        "priceDescription": "Offers over £495,000",
        "summary": "Detached Bungalow",
        "bedrooms": 3,
        "id": "01038b880532f95cc5d4a47139a3860a"
    },
    {
        "url": "https://www.sspc.co.uk/20-Milton-Crescent-EDINBURGH-EH15-3PQ-4-Bedroom-Detached-Bungalow-ESPC",
        "address": "20 Milton Crescent, EDINBURGH EH15 3PQ",
        "priceDescription": "Offers over £495,000",
        "summary": "Detached Bungalow",
        "bedrooms": 4,
        "id": "9c143441df5353184cbc44ef6c192500"
    },
    {
        "url": "https://www.sspc.co.uk/Fairview-Romanno-Bridge-West-Linton-EH46-7BY-4-Bedroom-Detached-Bungalow-ESPC",
        "address": "Fairview, Romanno Bridge, West Linton EH46 7BY",
        "priceDescription": "Offers over £490,000",
        "summary": "Detached Bungalow",
        "bedrooms": 4,
        "id": "2ff1135b31b609e8a37af16865b42a9c"
    },
    {
        "url": "https://www.sspc.co.uk/30-Ashley-Gardens-Edinburgh-EH11-1RW-4-Bedroom-Detached-Bungalow-ESPC",
        "address": "30 Ashley Gardens, Edinburgh EH11 1RW",
        "priceDescription": "Offers over £485,000",
        "summary": "Detached Bungalow",
        "bedrooms": 4,
        "id": "acdb19c8036e8eab467758096a113736"
    },
    {
        "url": "https://www.sspc.co.uk/5-North-Gyle-Drive-Corstorphine-Edinburgh-EH12-8JW-3-Bedroom-Detached-Bungalow-ESPC",
        "address": "5 North Gyle Drive, Corstorphine, Edinburgh EH12 8JW",
        "priceDescription": "Offers over £480,000",
        "summary": "Detached Bungalow",
        "bedrooms": 3,
        "id": "79731fcef5f17e6ed43cb3d29e00a628"
    },
    {
        "url": "https://www.sspc.co.uk/12-Broompark-Road-Edinburgh-EH12-7JZ-4-Bedroom-Semi-Detached-Bungalow-ESPC",
        "address": "12 Broompark Road, Edinburgh EH12 7JZ",
        "priceDescription": "Offers over £460,000",
        "summary": "Semi-Detached Bungalow",
        "bedrooms": 4,
        "id": "abc932ce2666f3651fe31c69b609ebe4"
    },
    {
        "url": "https://www.sspc.co.uk/1-Riverbank-Lodge-Main-Street-Crook-of-Devon-KINROSS-KY13-0UQ-5-Bedroom-Detached-Bungalow-ESPC",
        "address": "1 Riverbank Lodge, Main Street, Crook of Devon, KINROSS KY13 0UQ",
        "priceDescription": "Offers over £450,000",
        "summary": "Detached Bungalow",
        "bedrooms": 5,
        "id": "634b47d9d2d69a60c7cfca669d63b600"
    },
    {
        "url": "https://www.sspc.co.uk/17-Gladney-Ceres-CUPAR-KY15-5LT-5-Bedroom-Detached-Bungalow-ESPC",
        "address": "17 Gladney, Ceres, CUPAR KY15 5LT",
        "priceDescription": "Offers over £450,000",
        "summary": "Detached Bungalow",
        "bedrooms": 5,
        "id": "55624778808c00cfc21729ae5bd41376"
    },
    {
        "url": "https://www.sspc.co.uk/1-Netherview-Tweed-Road-TD1-3HG-3-Bedroom-Detached-Bungalow-BSPC",
        "address": "1 Netherview, Tweed Road TD1 3HG",
        "priceDescription": "Guide Price £440,000",
        "summary": "Detached Bungalow",
        "bedrooms": 3,
        "id": "fcd4af77f7bcb6844d82d7ed1b53e551"
    },
    {
        "url": "https://www.sspc.co.uk/1-Netherview-Tweed-Road-Galashiels-TD1-3HG-3-Bedroom-Detached-Bungalow-ESPC",
        "address": "1 Netherview, Tweed Road, Galashiels TD1 3HG",
        "priceDescription": "Guide Price £440,000",
        "summary": "Detached Bungalow",
        "bedrooms": 3,
        "id": "e2c68d2f3da970ac1b7bd0bed22988eb"
    },
    {
        "url": "https://www.sspc.co.uk/17-Newhailes-Crescent-Musselburgh-EH21-6DP-3-Bedroom-Detached-Bungalow-ESPC",
        "address": "17 Newhailes Crescent, Musselburgh EH21 6DP",
        "priceDescription": "Offers over £440,000",
        "summary": "Detached Bungalow",
        "bedrooms": 3,
        "id": "47eac18a26f0b8c7a3f58174c5c69296"
    },
    {
        "url": "https://www.sspc.co.uk/Mill-of-Fyall-Cottage-Alyth-PH11-8LB-3-Bedroom-Detached-Bungalow-PSPC",
        "address": "Mill of Fyall Cottage, Alyth PH11 8LB",
        "priceDescription": "Offers Over £425,000",
        "summary": "Detached Bungalow",
        "bedrooms": 3,
        "id": "ce033a6e9910a4092fe52c52522d6cbd"
    },
    {
        "url": "https://www.sspc.co.uk/Roslyn-Kindallachan-Pitlochry-PH9-0NW-3-Bedroom-Detached-Bungalow-PSPC",
        "address": "Roslyn, Kindallachan, Pitlochry PH9 0NW",
        "priceDescription": "Offers Over £425,000",
        "summary": "Detached Bungalow",
        "bedrooms": 3,
        "id": "37ec3a25e2e6a09b87037aeafb50b8f6"
    },
    {
        "url": "https://www.sspc.co.uk/39E-Old-Burdiehouse-Road-Burdiehouse-Edinburgh-EH17-8BQ-3-Bedroom-Detached-Bungalow-ESPC",
        "address": "39E, Old Burdiehouse Road, Burdiehouse, Edinburgh EH17 8BQ",
        "priceDescription": "Fixed Price £420,000",
        "summary": "Detached Bungalow",
        "bedrooms": 3,
        "id": "f498ffe5aaf1e981537343a8d4283831"
    },
    {
        "url": "https://www.sspc.co.uk/2-Ewingston-Cottages-Humbie-EH36-5PE-4-Bedroom-Terraced-Bungalow-ESPC",
        "address": "2 Ewingston Cottages, Humbie EH36 5PE",
        "priceDescription": "Offers over £415,000",
        "summary": "Terraced Bungalow",
        "bedrooms": 4,
        "id": "9415ae7728678323822369636ccb06b2"
    },
    {
        "url": "https://www.sspc.co.uk/Woodvale-Kippford-Dalbeattie-DG5-4LL-3-Bedroom-Detached-Bungalow-ESPC",
        "address": "Woodvale, Kippford, Dalbeattie DG5 4LL",
        "priceDescription": "Offers over £415,000",
        "summary": "Detached Bungalow",
        "bedrooms": 3,
        "id": "3c0371da93e045add5c67c4c96b7d929"
    },
    {
        "url": "https://www.sspc.co.uk/14-Auchmannoch-Avenue-Paisley-PA1-3AQ-3-Bedroom-Detached-Bungalow-ESPC",
        "address": "14 Auchmannoch Avenue, Paisley PA1 3AQ",
        "priceDescription": "Offers over £415,000",
        "summary": "Detached Bungalow",
        "bedrooms": 3,
        "id": "3c680dd04a9a7c31b96747843d686535"
    },
    {
        "url": "https://www.sspc.co.uk/39-Kingfisher-Road-Strathmore-Fields-Forfar-DD8-3FR-4-Bedroom-Detached-Bungalow-TSPC",
        "address": "39 Kingfisher Road, Strathmore Fields, Forfar DD8 3FR",
        "priceDescription": "Fixed £415,000",
        "summary": "Detached Bungalow",
        "bedrooms": 4,
        "id": "cd710afd41161c1b85589753070f0dca"
    },
    {
        "url": "https://www.sspc.co.uk/31-High-Street-KINROSS-KY13-8AA-4-Bedroom-Detached-Bungalow-ESPC",
        "address": "31 High Street, KINROSS KY13 8AA",
        "priceDescription": "Offers over £399,995",
        "summary": "Detached Bungalow",
        "bedrooms": 4,
        "id": "5cc9453d052dc5defde75776ee3ec0c1"
    },
    {
        "url": "https://www.sspc.co.uk/19-Burdiehouse-Road-Burdiehouse-EH17-8AE-3-Bedroom-Detached-Bungalow-ESPC",
        "address": "19 Burdiehouse Road, Burdiehouse EH17 8AE",
        "priceDescription": "Offers over £399,000",
        "summary": "Detached Bungalow",
        "bedrooms": 3,
        "id": "f62392aa5a9f71d93e50b1df8857ca89"
    },
    {
        "url": "https://www.sspc.co.uk/The-Dhorlin-6-Montgomerie-Road-PRESTWICK-KA9-1QT-4-Bedroom-Detached-Bungalow-ESPC",
        "address": "The Dhorlin, 6 Montgomerie Road, PRESTWICK KA9 1QT",
        "priceDescription": "Offers over £395,000",
        "summary": "Detached Bungalow",
        "bedrooms": 4,
        "id": "57ea65c73d0210bfac480bc1d5cad13c"
    },
    {
        "url": "https://www.sspc.co.uk/18-Lord-President-Road-North-Berwick-EH39-4RW-3-Bedroom-Detached-Bungalow-ESPC",
        "address": "18 Lord President Road, North Berwick EH39 4RW",
        "priceDescription": "Offers over £395,000",
        "summary": "Detached Bungalow",
        "bedrooms": 3,
        "id": "da241ce80433b5c5cafbdcf0428a51fb"
    },
    {
        "url": "https://www.sspc.co.uk/Sixfarthings-Newtonairds-DUMFRIES-DG2-0JL-4-Bedroom-Detached-Bungalow-ESPC",
        "address": "Sixfarthings, Newtonairds, DUMFRIES DG2 0JL",
        "priceDescription": "Offers over £390,000",
        "summary": "Detached Bungalow",
        "bedrooms": 4,
        "id": "f82488e44912aaa9ba23d9fe6aeb5d2a"
    },
    {
        "url": "https://www.sspc.co.uk/4-Gordon-Street-Broughty-Ferry-DD5-2RA-4-Bedroom-Detached-Bungalow-TSPC",
        "address": "4 Gordon Street, Broughty Ferry DD5 2RA",
        "priceDescription": "Offers Over £390,000",
        "summary": "Detached Bungalow",
        "bedrooms": 4,
        "id": "61b55fdb4421a544946560925d3545ae"
    },
    {
        "url": "https://www.sspc.co.uk/Cairnlea-Appletreehall-TD9-8PW-3-Bedroom-Detached-Bungalow-BSPC",
        "address": "Cairnlea, Appletreehall TD9 8PW",
        "priceDescription": "In the Region Of £385,000",
        "summary": "Detached Bungalow",
        "bedrooms": 3,
        "id": "f4f952bc208f8851bd447eea0beb6236"
    },
    {
        "url": "https://www.sspc.co.uk/6-Blairadam-Grove-Keltybridge-KELTY-KY4-0JU-3-Bedroom-Detached-Bungalow-ESPC",
        "address": "6 Blairadam Grove, Keltybridge, KELTY KY4 0JU",
        "priceDescription": "Fixed Price £385,000",
        "summary": "Detached Bungalow",
        "bedrooms": 3,
        "id": "b8cabe4336f9515ccb82999a0d1507cd"
    },
    {
        "url": "https://www.sspc.co.uk/Taronga-10-Rhonepark-Cresent-Crossmichael-.-DG7-3BN-3-Bedroom-Detached-Bungalow-ESPC",
        "address": "Taronga, 10 Rhonepark Cresent, Crossmichael, . DG7 3BN",
        "priceDescription": "Offers In The Region Of £380,000",
        "summary": "Detached Bungalow",
        "bedrooms": 3,
        "id": "3706a5ce26217ae6fee9b63dd1ae9b99"
    },
    {
        "url": "https://www.sspc.co.uk/35-Kingfisher-Road-Strathmore-Fields-Forfar-DD8-3FR-3-Bedroom-Detached-Bungalow-TSPC",
        "address": "35 Kingfisher Road, Strathmore Fields, Forfar DD8 3FR",
        "priceDescription": "Fixed £380,000",
        "summary": "Detached Bungalow",
        "bedrooms": 3,
        "id": "a3d02d53ce94ed1e552a648016aeed22"
    },
    {
        "url": "https://www.sspc.co.uk/195-Main-Street-EH37-5SQ-4-Bedroom-Detached-Bungalow-ESPC",
        "address": "195 Main Street EH37 5SQ",
        "priceDescription": "Fixed Price £375,000",
        "summary": "Detached Bungalow",
        "bedrooms": 4,
        "id": "8e20930c126d98d5659ddbf44b2c9337"
    },
    {
        "url": "https://www.sspc.co.uk/8-Balmoral-Drive-Bearsden-GLASGOW-G61-1DH-3-Bedroom-Detached-Bungalow-ESPC",
        "address": "8 Balmoral Drive, Bearsden, GLASGOW G61 1DH",
        "priceDescription": "Offers over £375,000",
        "summary": "Detached Bungalow",
        "bedrooms": 3,
        "id": "f015a20550426e919f1f0005accc86b3"
    },
    {
        "url": "https://www.sspc.co.uk/Butts-House-Leslie-Road-Scotlandwell-KINROSS-KY13-9JE-4-Bedroom-Detached-Bungalow-ESPC",
        "address": "Butts House, Leslie Road, Scotlandwell, KINROSS KY13 9JE",
        "priceDescription": "Offers over £375,000",
        "summary": "Detached Bungalow",
        "bedrooms": 4,
        "id": "8dbab8d01d93f57ec999e6f301ed1b68"
    },
    {
        "url": "https://www.sspc.co.uk/34-North-Latch-Road-Brechin-DD9-6LE-5-Bedroom-Detached-Bungalow-TSPC",
        "address": "34 North Latch Road, Brechin DD9 6LE",
        "priceDescription": "Offers Over £375,000",
        "summary": "Detached Bungalow",
        "bedrooms": 5,
        "id": "3a1cf832ae274e11f9ac7706ff3066cd"
    },
    {
        "url": "https://www.sspc.co.uk/4-Burns-Brae-Aberfeldy-PH15-2ER-3-Bedroom-Detached-Bungalow-PSPC",
        "address": "4 Burns Brae, Aberfeldy PH15 2ER",
        "priceDescription": "Offers Over £370,000",
        "summary": "Detached Bungalow",
        "bedrooms": 3,
        "id": "8b3eae31bc88058bf32f7d08d497a483"
    },
    {
        "url": "https://www.sspc.co.uk/7-Orchard-Court-East-Linton-East-Lothian-EH40-3EG-3-Bedroom-Detached-Bungalow-ESPC",
        "address": "7 Orchard Court, East Linton, East Lothian EH40 3EG",
        "priceDescription": "Offers over £365,000",
        "summary": "Detached Bungalow",
        "bedrooms": 3,
        "id": "f3374327ea1479d02d16c901b0440c92"
    },
    {
        "url": "https://www.sspc.co.uk/10-Ranfurly-Road-Bridge-Of-Weir-PA11-3EL-4-Bedroom-Detached-Bungalow-ESPC",
        "address": "10 Ranfurly Road, Bridge Of Weir PA11 3EL",
        "priceDescription": "Offers over £365,000",
        "summary": "Detached Bungalow",
        "bedrooms": 4,
        "id": "74621e76ab20392e93f86501a80188f7"
    },
    {
        "url": "https://www.sspc.co.uk/13-Balfour-Crescent-Milnathort-KINROSS-KY13-9TA-3-Bedroom-Detached-Bungalow-ESPC",
        "address": "13 Balfour Crescent, Milnathort, KINROSS KY13 9TA",
        "priceDescription": "Offers over £360,000",
        "summary": "Detached Bungalow",
        "bedrooms": 3,
        "id": "2a0163ce8105aa79b84146afd17e4bf1"
    },
    {
        "url": "https://www.sspc.co.uk/7-Arnott-Gardens-Edinburgh-EH14-2LB-2-Bedroom-Detached-Bungalow-ESPC",
        "address": "7 Arnott Gardens, Edinburgh EH14 2LB",
        "priceDescription": "Fixed Price £360,000",
        "summary": "Detached Bungalow",
        "bedrooms": 2,
        "id": "46e0bdf19be36c0f4a4a4b6569adaa19"
    },
    {
        "url": "https://www.sspc.co.uk/19-Craigentinny-Avenue-North-Craigentinny-Edinburgh-EH6-7LJ-4-Bedroom-Semi-Detached-Bungalow-ESPC",
        "address": "19 Craigentinny Avenue North, Craigentinny, Edinburgh EH6 7LJ",
        "priceDescription": "Fixed Price £355,000",
        "summary": "Semi-Detached Bungalow",
        "bedrooms": 4,
        "id": "508dda37119c4b36c134e05f435bceba"
    },
    {
        "url": "https://www.sspc.co.uk/27-Craigentinny-Avenue-Craigentinny-Edinburgh-EH7-6PU-3-Bedroom-Semi-Detached-Bungalow-ESPC",
        "address": "27 Craigentinny Avenue, Craigentinny, Edinburgh EH7 6PU",
        "priceDescription": "Offers over £355,000",
        "summary": "Semi-Detached Bungalow",
        "bedrooms": 3,
        "id": "f734b08f0ad517e76d9fcff7bbcc4d7c"
    },
    {
        "url": "https://www.sspc.co.uk/5-Seaview-Crescent-Edinburgh-EH15-2LU-2-Bedroom-Detached-Bungalow-ESPC",
        "address": "5 Seaview Crescent, Edinburgh EH15 2LU",
        "priceDescription": "Offers over £350,000",
        "summary": "Detached Bungalow",
        "bedrooms": 2,
        "id": "954a97ff7924332fe741b77eff65c47f"
    },
    {
        "url": "https://www.sspc.co.uk/Caberfeidh-(Incorporating-Annexe)-Shore-Road-Sannox-Isle-of-Arran-KA27-8JD-4-Bedroom-Detached-Bungalow-ESPC",
        "address": "Caberfeidh (Incorporating Annexe), Shore Road, Sannox, Isle of Arran KA27 8JD",
        "priceDescription": "Fixed Price £350,000",
        "summary": "Detached Bungalow",
        "bedrooms": 4,
        "id": "3429ba4d891760c25cc5739a4f0d4dd7"
    },
    {
        "url": "https://www.sspc.co.uk/5-Reresmount-Place-Broughty-Ferry-DD5-2SN-3-Bedroom-Detached-Bungalow-TSPC",
        "address": "5 Reresmount Place, Broughty Ferry DD5 2SN",
        "priceDescription": "Fixed £350,000",
        "summary": "Detached Bungalow",
        "bedrooms": 3,
        "id": "348fc5e87e04d35c188f135b369d38fb"
    },
    {
        "url": "https://www.sspc.co.uk/St-Margarets-Auchencastle-Beattock-Moffat-DG10-9SQ-3-Bedroom-Detached-Bungalow-ESPC",
        "address": "St Margarets Auchencastle, Beattock, Moffat DG10 9SQ",
        "priceDescription": "Offers over £345,000",
        "summary": "Detached Bungalow",
        "bedrooms": 3,
        "id": "ff33b161d14ebec98120b26228912355"
    },
    {
        "url": "https://www.sspc.co.uk/413-Gilmerton-Road-Liberton-EDINBURGH-EH17-7JJ-4-Bedroom-Detached-Bungalow-ESPC",
        "address": "413 Gilmerton Road, Liberton, EDINBURGH EH17 7JJ",
        "priceDescription": "Offers over £345,000",
        "summary": "Detached Bungalow",
        "bedrooms": 4,
        "id": "6052e729455f7f1c9571daf9a9cf08ab"
    },
    {
        "url": "https://www.sspc.co.uk/107-Captains-Road-EDINBURGH-EH17-8DT-3-Bedroom-Detached-Bungalow-ESPC",
        "address": "107 Captains Road, EDINBURGH EH17 8DT",
        "priceDescription": "Offers over £340,000",
        "summary": "Detached Bungalow",
        "bedrooms": 3,
        "id": "66db99b47c058f7713e68a703fcc3051"
    },
    {
        "url": "https://www.sspc.co.uk/Lymiebrae-Canonbie-DG14-0RD-3-Bedroom-Detached-Bungalow-ESPC",
        "address": "Lymiebrae, Canonbie DG14 0RD",
        "priceDescription": "Offers over £340,000",
        "summary": "Detached Bungalow",
        "bedrooms": 3,
        "id": "bec5925d9c322a03b8c00b5625af51cd"
    },
    {
        "url": "https://www.sspc.co.uk/Kilness-32-Abercromby-Road-Castle-Douglas-DG7-1BA-3-Bedroom-Detached-Bungalow-ESPC",
        "address": "Kilness, 32 Abercromby Road, Castle Douglas DG7 1BA",
        "priceDescription": "Offers In The Region Of £340,000",
        "summary": "Detached Bungalow",
        "bedrooms": 3,
        "id": "bb5a0c1ce5b0adda8c9ec81477884ee0"
    },
    {
        "url": "https://www.sspc.co.uk/18-Dechmont-Road-Edinburgh-EH12-8JP-2-Bedroom-Semi-Detached-Bungalow-ESPC",
        "address": "18 Dechmont Road, Edinburgh EH12 8JP",
        "priceDescription": "Offers over £340,000",
        "summary": "Semi-Detached Bungalow",
        "bedrooms": 2,
        "id": "29fc8318d0a4b997c970d3d8200124bd"
    },
    {
        "url": "https://www.sspc.co.uk/29-Kingfisher-Avenue-Strathmore-Fields-Forfar-DD8-3FS-3-Bedroom-Detached-Bungalow-TSPC",
        "address": "29 Kingfisher Avenue, Strathmore Fields, Forfar DD8 3FS",
        "priceDescription": "Fixed £335,000",
        "summary": "Detached Bungalow",
        "bedrooms": 3,
        "id": "5c2aa454aa0099d6e75152170d99e979"
    },
    {
        "url": "https://www.sspc.co.uk/38-Rosamunde-Pilcher-Drive-Longforgan-DD2-5EF-4-Bedroom-Detached-Bungalow-TSPC",
        "address": "38 Rosamunde Pilcher Drive, Longforgan DD2 5EF",
        "priceDescription": "Offers Over £335,000",
        "summary": "Detached Bungalow",
        "bedrooms": 4,
        "id": "27a3e58dd21a7d7069fe735a9cd1a874"
    },
    {
        "url": "https://www.sspc.co.uk/13-The-Latch-Cairneyhill-DUNFERMLINE-KY12-8UX-4-Bedroom-Detached-Bungalow-ESPC",
        "address": "13 The Latch, Cairneyhill, DUNFERMLINE KY12 8UX",
        "priceDescription": "Offers In The Region Of £329,000",
        "summary": "Detached Bungalow",
        "bedrooms": 4,
        "id": "a6f8d839d654ed5be9291f175b54938d"
    },
    {
        "url": "https://www.sspc.co.uk/1-Dovecot-Lane-TD7-4BF-3-Bedroom-Detached-Bungalow-BSPC",
        "address": "1 Dovecot Lane TD7 4BF",
        "priceDescription": "Offers Over £325,000",
        "summary": "Detached Bungalow",
        "bedrooms": 3,
        "id": "dc42abf2b1bb4f3ca136d92853f35c71"
    },
    {
        "url": "https://www.sspc.co.uk/8B-Mary-Countess-Way-Glamis-DD8-1RF-4-Bedroom-Detached-Bungalow-TSPC",
        "address": "8B Mary Countess Way, Glamis DD8 1RF",
        "priceDescription": "Offers Over £325,000",
        "summary": "Detached Bungalow",
        "bedrooms": 4,
        "id": "3bd4f5297caf2c6e614af04e89c53f25"
    },
    {
        "url": "https://www.sspc.co.uk/Southpark-Edinburgh-Road-DUMFRIES-DG1-1SE-4-Bedroom-Detached-Bungalow-ESPC",
        "address": "Southpark, Edinburgh Road, DUMFRIES DG1 1SE",
        "priceDescription": "Offers over £320,000",
        "summary": "Detached Bungalow",
        "bedrooms": 4,
        "id": "dc4b1ce12cda88be4b8c2127d79e4945"
    },
    {
        "url": "https://www.sspc.co.uk/6a-Guthrie-Street-Letham-DD8-2PS-4-Bedroom-Detached-Bungalow-TSPC",
        "address": "6a Guthrie Street, Letham DD8 2PS",
        "priceDescription": "Offers Over £320,000",
        "summary": "Detached Bungalow",
        "bedrooms": 4,
        "id": "641f043ad79bc98399b8b9c411900ed1"
    },
    {
        "url": "https://www.sspc.co.uk/7-Pardovan-Holdings-LINLITHGOW-EH49-7RU-3-Bedroom-Detached-Bungalow-ESPC",
        "address": "7 Pardovan Holdings, LINLITHGOW EH49 7RU",
        "priceDescription": "Fixed Price £315,000",
        "summary": "Detached Bungalow",
        "bedrooms": 3,
        "id": "b6643e70efa7bef933ad4ab6e04f6e2a"
    },
    {
        "url": "https://www.sspc.co.uk/4-Springwood-Rise-TD5-8BE-3-Bedroom-Detached-Bungalow-BSPC",
        "address": "4 Springwood Rise TD5 8BE",
        "priceDescription": "Offers Over £310,000",
        "summary": "Detached Bungalow",
        "bedrooms": 3,
        "id": "b375ca79365779c115ff9ef26cb2708e"
    },
    {
        "url": "https://www.sspc.co.uk/18-Still-Haugh-Fountainhall-GALASHIELS-TD1-2SL-3-Bedroom-Detached-Bungalow-ESPC",
        "address": "18 Still Haugh, Fountainhall, GALASHIELS TD1 2SL",
        "priceDescription": "Offers over £310,000",
        "summary": "Detached Bungalow",
        "bedrooms": 3,
        "id": "e269c088c1a2f4dfba1c33d49a968978"
    },
    {
        "url": "https://www.sspc.co.uk/21-Still-Haugh-TD1-2SL-3-Bedroom-Detached-Bungalow-BSPC",
        "address": "21 Still Haugh TD1 2SL",
        "priceDescription": "Guide Price £300,000",
        "summary": "Detached Bungalow",
        "bedrooms": 3,
        "id": "6275a7f2fdea3c6bf5e48cff19906653"
    },
    {
        "url": "https://www.sspc.co.uk/3-Elizabeth-Street-Alyth-PH11-8FN-3-Bedroom-Detached-Bungalow-PSPC",
        "address": "3 Elizabeth Street, Alyth PH11 8FN",
        "priceDescription": "Fixed £300,000",
        "summary": "Detached Bungalow",
        "bedrooms": 3,
        "id": "0628c241f5784a54b6c751a484ed82be"
    },
    {
        "url": "https://www.sspc.co.uk/3-Templehall-Place-Newbigging-DD5-3UW-3-Bedroom-Detached-Bungalow-TSPC",
        "address": "3 Templehall Place, Newbigging DD5 3UW",
        "priceDescription": "Offers Over £300,000",
        "summary": "Detached Bungalow",
        "bedrooms": 3,
        "id": "aec775a6125f270c539a31d48cbf85c0"
    },
    {
        "url": "https://www.sspc.co.uk/3-Elizabeth-Street-Pitnacree-Park-Alyth-PH11-8FN-3-Bedroom-Detached-Bungalow-TSPC",
        "address": "3 Elizabeth Street, Pitnacree Park, Alyth PH11 8FN",
        "priceDescription": "Fixed £300,000",
        "summary": "Detached Bungalow",
        "bedrooms": 3,
        "id": "aa9237249c72fe95c0735d6c44aafcfa"
    },
    {
        "url": "https://www.sspc.co.uk/16-Montgomerie-Terrace-Gattonside-Melrose-TD6-9NT-3-Bedroom-Detached-Bungalow-BSPC",
        "address": "16 Montgomerie Terrace, Gattonside, Melrose TD6 9NT",
        "priceDescription": "Guide Price £295,000",
        "summary": "Detached Bungalow",
        "bedrooms": 3,
        "id": "93ad7705ba622bd64b31f5baf9d1f45b"
    },
    {
        "url": "https://www.sspc.co.uk/14-Carmelite-Road-South-Queensferry-EH30-9LU-2-Bedroom-Semi-Detached-Bungalow-ESPC",
        "address": "14 Carmelite Road, South Queensferry EH30 9LU",
        "priceDescription": "Offers over £295,000",
        "summary": "Semi-Detached Bungalow",
        "bedrooms": 2,
        "id": "41301c39c78f0f689aa6c679b757bdb3"
    },
    {
        "url": "https://www.sspc.co.uk/10-Ardestie-Street-Monifieth-DD5-4PR-3-Bedroom-Detached-Bungalow-TSPC",
        "address": "10 Ardestie Street, Monifieth DD5 4PR",
        "priceDescription": "Offers Over £290,000",
        "summary": "Detached Bungalow",
        "bedrooms": 3,
        "id": "52ac5940b46d141d2f976b61936d854e"
    },
    {
        "url": "https://www.sspc.co.uk/214-Millfield-Hill-Erskine-PA8-6JL-3-Bedroom-Detached-Bungalow-ESPC",
        "address": "214 Millfield Hill, Erskine PA8 6JL",
        "priceDescription": "Offers over £285,000",
        "summary": "Detached Bungalow",
        "bedrooms": 3,
        "id": "54bb0d2ec4852a9db7c9f99e9fa1be41"
    },
    {
        "url": "https://www.sspc.co.uk/Rosebank-Lodge-Bankend-Road-DUMFRIES-DG1-4TN-3-Bedroom-Detached-Bungalow-ESPC",
        "address": "Rosebank Lodge, Bankend Road, DUMFRIES DG1 4TN",
        "priceDescription": "Offers In The Region Of £285,000",
        "summary": "Detached Bungalow",
        "bedrooms": 3,
        "id": "0fcda27ab9c14b26ef25ff0c7f4582a3"
    },
    {
        "url": "https://www.sspc.co.uk/33-Robertson-Road-CUPAR-KY15-5YR-3-Bedroom-Detached-Bungalow-ESPC",
        "address": "33 Robertson Road, CUPAR KY15 5YR",
        "priceDescription": "Offers over £285,000",
        "summary": "Detached Bungalow",
        "bedrooms": 3,
        "id": "a12c729e0504cdedf4fe1e56b2cd0113"
    },
    {
        "url": "https://www.sspc.co.uk/3-Lochlands-Park-Arbroath-DD11-3SR-5-Bedroom-Detached-Bungalow-TSPC",
        "address": "3 Lochlands Park, Arbroath DD11 3SR",
        "priceDescription": "Offers Over £285,000",
        "summary": "Detached Bungalow",
        "bedrooms": 5,
        "id": "4c814569009a19425a4a6b7d55a9de7f"
    },
    {
        "url": "https://www.sspc.co.uk/28-Iona-Park-GLENROTHES-KY7-6NU-4-Bedroom-Detached-Bungalow-ESPC",
        "address": "28 Iona Park, GLENROTHES KY7 6NU",
        "priceDescription": "Offers over £280,000",
        "summary": "Detached Bungalow",
        "bedrooms": 4,
        "id": "13100820355667c8b04a98fa207e0b09"
    },
    {
        "url": "https://www.sspc.co.uk/Kendarroch-Dalry-CASTLE-DOUGLAS-DG7-3TX-3-Bedroom-Detached-Bungalow-ESPC",
        "address": "Kendarroch, Dalry, CASTLE DOUGLAS DG7 3TX",
        "priceDescription": "Offers over £280,000",
        "summary": "Detached Bungalow",
        "bedrooms": 3,
        "id": "2b7e4d590ad3dad8b7182e7bdff8e845"
    },
    {
        "url": "https://www.sspc.co.uk/Craigellachie-Blackwaterfoot-ISLE-OF-ARRAN-KA27-8HB-4-Bedroom-Detached-Bungalow-ESPC",
        "address": "Craigellachie, Blackwaterfoot, ISLE OF ARRAN KA27 8HB",
        "priceDescription": "Offers over £279,995",
        "summary": "Detached Bungalow",
        "bedrooms": 4,
        "id": "942ef224555c781ff677f845e93e1077"
    },
    {
        "url": "https://www.sspc.co.uk/2-Lochwood-Park-Kingseat-DUNFERMLINE-KY12-0UX-3-Bedroom-Detached-Bungalow-ESPC",
        "address": "2 Lochwood Park, Kingseat, DUNFERMLINE KY12 0UX",
        "priceDescription": "Fixed Price £279,950",
        "summary": "Detached Bungalow",
        "bedrooms": 3,
        "id": "b6dd93087b2d54858bc866890ff59eef"
    },
    {
        "url": "https://www.sspc.co.uk/Lismore-13-Mount-Pleasant-Road-KIRKCUDBRIGHT-DG6-4HG-3-Bedroom-Detached-Bungalow-ESPC",
        "address": "Lismore 13 Mount Pleasant Road, KIRKCUDBRIGHT DG6 4HG",
        "priceDescription": "Offers over £270,000",
        "summary": "Detached Bungalow",
        "bedrooms": 3,
        "id": "d813d802165923cc27db1a29d1014c18"
    },
    {
        "url": "https://www.sspc.co.uk/3-Fergus-Road-KIRKCUDBRIGHT-DG6-4HN-3-Bedroom-Detached-Bungalow-ESPC",
        "address": "3 Fergus Road, KIRKCUDBRIGHT DG6 4HN",
        "priceDescription": "Offers over £270,000",
        "summary": "Detached Bungalow",
        "bedrooms": 3,
        "id": "cee9cf9b7c7838462cbbbb4f3bb4293c"
    },
    {
        "url": "https://www.sspc.co.uk/9-Waulkmill-Letham-Grange-Arbroath-DD11-4QU-4-Bedroom-Detached-Bungalow-TSPC",
        "address": "9 Waulkmill, Letham Grange, Arbroath  DD11 4QU",
        "priceDescription": "Offers Over £270,000",
        "summary": "Detached Bungalow",
        "bedrooms": 4,
        "id": "1d5753ba10fc9f66f87e707c5fd97e97"
    },
    {
        "url": "https://www.sspc.co.uk/4-Auld-Mart-Road-Milnathort-KINROSS-KY13-9FR-3-Bedroom-Detached-Bungalow-ESPC",
        "address": "4 Auld Mart Road, Milnathort, KINROSS KY13 9FR",
        "priceDescription": "Offers over £265,000",
        "summary": "Detached Bungalow",
        "bedrooms": 3,
        "id": "698da02127f48e29259c7c845ac72087"
    },
    {
        "url": "https://www.sspc.co.uk/18-Mill-Gardens-Powmill-DOLLAR-FK14-7LQ-3-Bedroom-Detached-Bungalow-ESPC",
        "address": "18 Mill Gardens, Powmill, DOLLAR FK14 7LQ",
        "priceDescription": "Offers over £265,000",
        "summary": "Detached Bungalow",
        "bedrooms": 3,
        "id": "69dd9b09a4d05f8fc1cc32198d6bb52d"
    },
    {
        "url": "https://www.sspc.co.uk/47-Auld-Mart-Road-Milnathort-KY13-9FR-3-Bedroom-Detached-Bungalow-PSPC",
        "address": "47 Auld Mart Road, Milnathort KY13 9FR",
        "priceDescription": "Offers Over £265,000",
        "summary": "Detached Bungalow",
        "bedrooms": 3,
        "id": "476ae9d81d96c64f52c3d8135ac6df5e"
    },
    {
        "url": "https://www.sspc.co.uk/Dunain-Anderson-Street-Newburgh-KY14-6AE-3-Bedroom-Detached-Bungalow-PSPC",
        "address": "Dunain, Anderson Street, Newburgh KY14 6AE",
        "priceDescription": "Offers Over £265,000",
        "summary": "Detached Bungalow",
        "bedrooms": 3,
        "id": "7905e238929549090b64409060a75999"
    },
    {
        "url": "https://www.sspc.co.uk/Mossband-Dumfries-Road-Kirkgunzeon-DUMFRIES-DG2-8JP-4-Bedroom-Detached-Bungalow-ESPC",
        "address": "Mossband Dumfries Road, Kirkgunzeon, DUMFRIES DG2 8JP",
        "priceDescription": "Offers over £260,000",
        "summary": "Detached Bungalow",
        "bedrooms": 4,
        "id": "33e75b7ab6402fd5a841bfedb43ae10d"
    },
    {
        "url": "https://www.sspc.co.uk/Birchfield-9-Alma-Avenue-Aberfeldy-PH15-2BW-3-Bedroom-Detached-Bungalow-PSPC",
        "address": "Birchfield, 9 Alma Avenue, Aberfeldy PH15 2BW",
        "priceDescription": "Offers Over £260,000",
        "summary": "Detached Bungalow",
        "bedrooms": 3,
        "id": "b33e940f967e20803e2e94eeb942eb2e"
    },
    {
        "url": "https://www.sspc.co.uk/Ellerne-Old-Brechin-Road-Forfar-DD8-3DX-4-Bedroom-Detached-Bungalow-TSPC",
        "address": "Ellerne, Old Brechin Road, Forfar DD8 3DX",
        "priceDescription": "Fixed £260,000",
        "summary": "Detached Bungalow",
        "bedrooms": 4,
        "id": "912479c40dad47a41fd855dee226e728"
    },
    {
        "url": "https://www.sspc.co.uk/10-West-Crook-Way-Crook-of-Devon-KINROSS-KY13-0PH-2-Bedroom-Detached-Bungalow-ESPC",
        "address": "10 West Crook Way, Crook of Devon, KINROSS KY13 0PH",
        "priceDescription": "Offers over £259,500",
        "summary": "Detached Bungalow",
        "bedrooms": 2,
        "id": "d9da70ce910f6bb8c9b41a0ac0e520d3"
    },
    {
        "url": "https://www.sspc.co.uk/Achnacarry-10-Craig-en-Ros-Road-Millport-ISLE-OF-CUMBRAE-KA28-0BH-3-Bedroom-Detached-Bungalow-ESPC",
        "address": "Achnacarry, 10 Craig-en-Ros Road, Millport, ISLE OF CUMBRAE KA28 0BH",
        "priceDescription": "Offers over £255,000",
        "summary": "Detached Bungalow",
        "bedrooms": 3,
        "id": "61cc148ef734944d0a7657f3d058c1ca"
    },
    {
        "url": "https://www.sspc.co.uk/35-West-Myrescroft-TD8-6XR-3-Bedroom-Bungalow-BSPC",
        "address": "35 West Myrescroft TD8 6XR",
        "priceDescription": "Guide Price £250,000",
        "summary": "Bungalow",
        "bedrooms": 3,
        "id": "5ea0eca1b314fcdb696432a2e5b20650"
    },
    {
        "url": "https://www.sspc.co.uk/Eildon-View-Orchard-Park-TD6-9AR-2-Bedroom-Detached-Bungalow-BSPC",
        "address": "Eildon View, Orchard Park TD6 9AR",
        "priceDescription": "Offers Over £250,000",
        "summary": "Detached Bungalow",
        "bedrooms": 2,
        "id": "092a3368e0da7926ae6b2cecb10ce400"
    },
    {
        "url": "https://www.sspc.co.uk/Arkleton-Cottage-1-Crowbyres-TD9-9SN-2-Bedroom-Detached-Bungalow-BSPC",
        "address": "Arkleton Cottage 1 Crowbyres TD9 9SN",
        "priceDescription": "In the Region Of £250,000",
        "summary": "Detached Bungalow",
        "bedrooms": 2,
        "id": "1c9e74d96111c8505ebe18ed371bc274"
    },
    {
        "url": "https://www.sspc.co.uk/Mill-Hollow-2-Mill-Road-Haugh-of-Urr-DG7-3YB-3-Bedroom-Detached-Bungalow-ESPC",
        "address": "Mill Hollow, 2 Mill Road, Haugh of Urr DG7 3YB",
        "priceDescription": "Offers In The Region Of £250,000",
        "summary": "Detached Bungalow",
        "bedrooms": 3,
        "id": "b6384d6e97cc32c0e00ce25ce4bf1f8a"
    },
    {
        "url": "https://www.sspc.co.uk/Arkleton-Cottage-1-Crowbyres-Hawick-TD9-9SN-2-Bedroom-Detached-Bungalow-ESPC",
        "address": "Arkleton Cottage, 1 Crowbyres, Hawick TD9 9SN",
        "priceDescription": "Offers In The Region Of £250,000",
        "summary": "Detached Bungalow",
        "bedrooms": 2,
        "id": "895388da7b53385d5fd278ba406ab38f"
    },
    {
        "url": "https://www.sspc.co.uk/Westerly-Milton-Lane-Finavon-DD8-3RH-4-Bedroom-Detached-Bungalow-TSPC",
        "address": "Westerly, Milton Lane, Finavon DD8 3RH",
        "priceDescription": "Around £250,000",
        "summary": "Detached Bungalow",
        "bedrooms": 4,
        "id": "4b2a8ddd05040ecb19e1112cfb086184"
    },
    {
        "url": "https://www.sspc.co.uk/12-Factors-Park-TD2-6QW-3-Bedroom-Semi-Detached-Bungalow-BSPC",
        "address": "12 Factors Park TD2 6QW",
        "priceDescription": "Guide Price £245,000",
        "summary": "Semi-Detached Bungalow",
        "bedrooms": 3,
        "id": "9ff1c92e957c4ac60aaa3212f8680967"
    },
    {
        "url": "https://www.sspc.co.uk/12-Factors-Park-Lauder-TD2-6QW-3-Bedroom-Semi-Detached-Bungalow-ESPC",
        "address": "12 Factors Park, Lauder TD2 6QW",
        "priceDescription": "Guide Price £245,000",
        "summary": "Semi-Detached Bungalow",
        "bedrooms": 3,
        "id": "ae5fe3f89d0784f6ad50d2647ef8c498"
    },
    {
        "url": "https://www.sspc.co.uk/37-Gray-Street-PRESTWICK-KA9-1LX-3-Bedroom-Detached-Bungalow-ESPC",
        "address": "37 Gray Street, PRESTWICK KA9 1LX",
        "priceDescription": "Offers over £245,000",
        "summary": "Detached Bungalow",
        "bedrooms": 3,
        "id": "bf58ca6a8f96a08136b8b2094a110850"
    },
    {
        "url": "https://www.sspc.co.uk/27-Dundas-Place-Kirkliston-EH29-9BJ-4-Bedroom-Semi-Detached-Bungalow-ESPC",
        "address": "27 Dundas Place, Kirkliston EH29 9BJ",
        "priceDescription": "Offers over £245,000",
        "summary": "Semi-Detached Bungalow",
        "bedrooms": 4,
        "id": "9e201a25dae6ffcf72d4796066f97829"
    },
    {
        "url": "https://www.sspc.co.uk/24-Robertson-Road-CUPAR-KY15-5YR-2-Bedroom-Detached-Bungalow-ESPC",
        "address": "24 Robertson Road, CUPAR KY15 5YR",
        "priceDescription": "Offers over £240,000",
        "summary": "Detached Bungalow",
        "bedrooms": 2,
        "id": "1657e8b2ac03ee01ad5b4d55f9779fb0"
    },
    {
        "url": "https://www.sspc.co.uk/1-Beechgrove-LOCKERBIE-DG11-2QS-2-Bedroom-Detached-Bungalow-ESPC",
        "address": "1 Beechgrove, LOCKERBIE DG11 2QS",
        "priceDescription": "Guide Price £240,000",
        "summary": "Detached Bungalow",
        "bedrooms": 2,
        "id": "dd40bc6588ff9bed2338eadf78a8b1fc"
    },
    {
        "url": "https://www.sspc.co.uk/3-Mid-Nunnery-Irongray-Road-DUMFRIES-DG2-0HS-4-Bedroom-Detached-Bungalow-ESPC",
        "address": "3 Mid Nunnery, Irongray Road, DUMFRIES DG2 0HS",
        "priceDescription": "Offers over £240,000",
        "summary": "Detached Bungalow",
        "bedrooms": 4,
        "id": "d6265cd6734c67135d19e0fce0f841d9"
    },
    {
        "url": "https://www.sspc.co.uk/The-Firs-Kirkmichael-PH10-7LY-2-Bedroom-Detached-Bungalow-PSPC",
        "address": "The Firs, Kirkmichael PH10 7LY",
        "priceDescription": "Offers Over £240,000",
        "summary": "Detached Bungalow",
        "bedrooms": 2,
        "id": "ecd43d97358f245370f70b05e7351134"
    },
    {
        "url": "https://www.sspc.co.uk/5-Dundarach-Gardens-Pitlochry-PH16-5DX-2-Bedroom-Detached-Bungalow-PSPC",
        "address": "5 Dundarach Gardens, Pitlochry PH16 5DX",
        "priceDescription": "Offers Over £240,000",
        "summary": "Detached Bungalow",
        "bedrooms": 2,
        "id": "c11698c322d9147dc5c2337ff76ee8b9"
    },
    {
        "url": "https://www.sspc.co.uk/9-The-Grove-Auchterarder-PH3-1PT-2-Bedroom-Detached-Bungalow-PSPC",
        "address": "9 The Grove, Auchterarder PH3 1PT",
        "priceDescription": "Offers Over £240,000",
        "summary": "Detached Bungalow",
        "bedrooms": 2,
        "id": "5d87246d10fad2a102c6d2102c7c96d5"
    },
    {
        "url": "https://www.sspc.co.uk/2-Bridgend-of-Carse-Cottages-The-Grange-Errol-PH2-7TB-3-Bedroom-Terraced-Bungalow-PSPC",
        "address": "2 Bridgend of Carse Cottages, The Grange, Errol PH2 7TB",
        "priceDescription": "Offers Over £240,000",
        "summary": "Terraced Bungalow",
        "bedrooms": 3,
        "id": "e1f965fc3955e9ae7aca7c4191d4028c"
    },
    {
        "url": "https://www.sspc.co.uk/14-Geirston-Road-Kilbirnie-KA25-7LG-2-Bedroom-Detached-Bungalow-ESPC",
        "address": "14 Geirston Road, Kilbirnie KA25 7LG",
        "priceDescription": "Offers over £239,999",
        "summary": "Detached Bungalow",
        "bedrooms": 2,
        "id": "92a0611155db156354146381607a6299"
    },
    {
        "url": "https://www.sspc.co.uk/5-Burnside-Gardens-KIRKCUDBRIGHT-DG6-4JY-2-Bedroom-Detached-Bungalow-ESPC",
        "address": "5 Burnside Gardens, KIRKCUDBRIGHT DG6 4JY",
        "priceDescription": "Offers over £239,500",
        "summary": "Detached Bungalow",
        "bedrooms": 2,
        "id": "dcc8a42e7663bcf908aba473e57972b1"
    },
    {
        "url": "https://www.sspc.co.uk/3-Winton-Way-Tranent-EH33-2QD-3-Bedroom-Detached-Bungalow-ESPC",
        "address": "3 Winton Way, Tranent EH33 2QD",
        "priceDescription": "Offers over £235,000",
        "summary": "Detached Bungalow",
        "bedrooms": 3,
        "id": "c53399c25814440bee3b2b1c0637fec6"
    },
    {
        "url": "https://www.sspc.co.uk/81-Denoon-Terrace-Dundee-DD2-2DG-3-Bedroom-Semi-Detached-Bungalow-TSPC",
        "address": "81 Denoon Terrace, Dundee DD2 2DG",
        "priceDescription": "Offers Over £235,000",
        "summary": "Semi-Detached Bungalow",
        "bedrooms": 3,
        "id": "b60990299a13d5186220901f5a6ff7fb"
    },
    {
        "url": "https://www.sspc.co.uk/29-Tullideph-Road-Dundee-DD2-2JD-3-Bedroom-Detached-Bungalow-TSPC",
        "address": "29 Tullideph Road, Dundee DD2 2JD",
        "priceDescription": "Fixed £235,000",
        "summary": "Detached Bungalow",
        "bedrooms": 3,
        "id": "26e82a79a5e20b2419dac67340784add"
    },
    {
        "url": "https://www.sspc.co.uk/1-Ebroch-Park-Kilsyth-G65-0PQ-3-Bedroom-Detached-Bungalow-ESPC",
        "address": "1 Ebroch Park, Kilsyth G65 0PQ",
        "priceDescription": "Offers over £234,995",
        "summary": "Detached Bungalow",
        "bedrooms": 3,
        "id": "88b41bd194596d72fc51ffd37235a104"
    },
    {
        "url": "https://www.sspc.co.uk/Phase-3-Pitcrocknie-Village-Alyth-PH11-8JJ-2-Bedroom-Detached-Bungalow-PSPC",
        "address": "Phase 3, Pitcrocknie Village, Alyth PH11 8JJ",
        "priceDescription": "From £232,950",
        "summary": "Detached Bungalow",
        "bedrooms": 2,
        "id": "7b4d6225877ab5d04bdd3cd6611890df"
    },
    {
        "url": "https://www.sspc.co.uk/Braeholm-Old-Bridge-Road-TD7-5DF-3-Bedroom-Bungalow-BSPC",
        "address": "Braeholm, Old Bridge Road TD7 5DF",
        "priceDescription": "Offers Over £230,000",
        "summary": "Bungalow",
        "bedrooms": 3,
        "id": "ce1cd5c862c4f568597972c21877dfd2"
    },
    {
        "url": "https://www.sspc.co.uk/Ingleby-Carbostmore-Carbost-ISLE-OF-SKYE-IV47-8ST-3-Bedroom-Detached-Bungalow-ESPC",
        "address": "Ingleby, Carbostmore, Carbost, ISLE OF SKYE IV47 8ST",
        "priceDescription": "Offers In The Region Of £230,000",
        "summary": "Detached Bungalow",
        "bedrooms": 3,
        "id": "1c032f59bdab481a3d84144b4a830340"
    },
    {
        "url": "https://www.sspc.co.uk/Boswell-Cottage-New-Gilston-LEVEN-KY8-5TF-2-Bedroom-Detached-Bungalow-ESPC",
        "address": "Boswell Cottage, New Gilston, LEVEN KY8 5TF",
        "priceDescription": "Offers over £230,000",
        "summary": "Detached Bungalow",
        "bedrooms": 2,
        "id": "691e733b7a3d272d5e6568224107236b"
    },
    {
        "url": "https://www.sspc.co.uk/3-Netherhall-Place-Bridge-of-Dee-CASTLE-DOUGLAS-DG7-1TS-3-Bedroom-Detached-Bungalow-ESPC",
        "address": "3 Netherhall Place, Bridge of Dee, CASTLE DOUGLAS DG7 1TS",
        "priceDescription": "Offers over £230,000",
        "summary": "Detached Bungalow",
        "bedrooms": 3,
        "id": "440e57f5e28ba9c880a0b001df325a41"
    },
    {
        "url": "https://www.sspc.co.uk/18-Cairnie-Road-Arbroath-DD11-3DY-3-Bedroom-Detached-Bungalow-TSPC",
        "address": "18 Cairnie Road, Arbroath DD11 3DY",
        "priceDescription": "Offers Over £230,000",
        "summary": "Detached Bungalow",
        "bedrooms": 3,
        "id": "02df66aa21b337c048ddb0bdc8ebf1b6"
    },
    {
        "url": "https://www.sspc.co.uk/The-Skyline-Barry-Downs-Barry-Carnoustie-DD7-7SA-3-Bedroom-Detached-Bungalow-TSPC",
        "address": "The Skyline, Barry Downs, Barry, Carnoustie DD7 7SA",
        "priceDescription": "Fixed £230,000",
        "summary": "Detached Bungalow",
        "bedrooms": 3,
        "id": "afdaaa24a2612b8ba4375f937971ac43"
    },
    {
        "url": "https://www.sspc.co.uk/34-Barntongate-Terrace-Edinburgh-EH4-8BU-2-Bedroom-Terraced-Bungalow-ESPC",
        "address": "34 Barntongate Terrace, Edinburgh EH4 8BU",
        "priceDescription": "Fixed Price £229,950",
        "summary": "Terraced Bungalow",
        "bedrooms": 2,
        "id": "247034ab1649b594c0e0b68194b43e7d"
    },
    {
        "url": "https://www.sspc.co.uk/The-Sheiling-Carsluith-NEWTON-STEWART-DG8-7DN-2-Bedroom-Detached-Bungalow-ESPC",
        "address": "The Sheiling, Carsluith, NEWTON STEWART DG8 7DN",
        "priceDescription": "Offers over £225,000",
        "summary": "Detached Bungalow",
        "bedrooms": 2,
        "id": "7b1db4a42fd5e0a2ccc436175568d448"
    },
    {
        "url": "https://www.sspc.co.uk/6-Provost-Park-Auchtermuchty-CUPAR-KY14-7DT-3-Bedroom-Semi-Detached-Bungalow-ESPC",
        "address": "6 Provost Park, Auchtermuchty, CUPAR KY14 7DT",
        "priceDescription": "Offers over £225,000",
        "summary": "Semi-Detached Bungalow",
        "bedrooms": 3,
        "id": "a272748f54bd88be55a5ca61b7ef3a48"
    },
    {
        "url": "https://www.sspc.co.uk/45-Charleston-Drive-Dundee-DD2-2HE-4-Bedroom-Semi-Detached-Bungalow-TSPC",
        "address": "45 Charleston Drive, Dundee DD2 2HE",
        "priceDescription": "Offers Over £225,000",
        "summary": "Semi-Detached Bungalow",
        "bedrooms": 4,
        "id": "873913c592fde45939f3d5179f8b113b"
    },
    {
        "url": "https://www.sspc.co.uk/4-Cedar-Way-Friockheim-DD11-4WG-2-Bedroom-Detached-Bungalow-TSPC",
        "address": "4 Cedar Way, Friockheim DD11 4WG",
        "priceDescription": "Offers Over £225,000",
        "summary": "Detached Bungalow",
        "bedrooms": 2,
        "id": "cfa2298b4a80a923b0104c1a32a7ad66"
    },
    {
        "url": "https://www.sspc.co.uk/Burnside-Cottage-Kirk-Wynd-Dunning-PH2-0SJ-2-Bedroom-Detached-Bungalow-PSPC",
        "address": "Burnside Cottage, Kirk Wynd, Dunning PH2 0SJ",
        "priceDescription": "Offers Over £220,000",
        "summary": "Detached Bungalow",
        "bedrooms": 2,
        "id": "580a9c681612944fc90574d1548ca943"
    },
    {
        "url": "https://www.sspc.co.uk/Speybank-10-Letham-Road-Perth-PH1-2AP-2-Bedroom-Detached-Bungalow-PSPC",
        "address": "Speybank, 10 Letham Road, Perth PH1 2AP",
        "priceDescription": "Offers Over £220,000",
        "summary": "Detached Bungalow",
        "bedrooms": 2,
        "id": "549bc42996e4b5e59006e105e4560d89"
    },
    {
        "url": "https://www.sspc.co.uk/24-Hospitalfield-Road-Arbroath-DD11-2LS-3-Bedroom-Detached-Bungalow-TSPC",
        "address": "24 Hospitalfield Road, Arbroath DD11 2LS",
        "priceDescription": "Offers Over £220,000",
        "summary": "Detached Bungalow",
        "bedrooms": 3,
        "id": "1ff51a6f72aa7a3a6bb54bf18689ac7b"
    },
    {
        "url": "https://www.sspc.co.uk/3-Northampton-Road-Forfar-DD8-1JG-2-Bedroom-Detached-Bungalow-TSPC",
        "address": "3 Northampton Road, Forfar DD8 1JG",
        "priceDescription": "Offers Over £220,000",
        "summary": "Detached Bungalow",
        "bedrooms": 2,
        "id": "f3aaa0d815c7402443aa786ab017033e"
    },
    {
        "url": "https://www.sspc.co.uk/5-Kyle-Court-Cumnock-KA18-1DL-3-Bedroom-Detached-Bungalow-ESPC",
        "address": "5 Kyle Court, Cumnock KA18 1DL",
        "priceDescription": "Offers over £219,999",
        "summary": "Detached Bungalow",
        "bedrooms": 3,
        "id": "7d6da4ed584e7f4d7943bd268941f1ab"
    },
    {
        "url": "https://www.sspc.co.uk/14-Bennecourt-Crescent-TD12-4BX-3-Bedroom-Detached-Bungalow-BSPC",
        "address": "14 Bennecourt Crescent TD12 4BX",
        "priceDescription": "Offers Over £215,000",
        "summary": "Detached Bungalow",
        "bedrooms": 3,
        "id": "b0fdade0ec40bff475ee8ef7a14b11d0"
    },
    {
        "url": "https://www.sspc.co.uk/Shadwell-Balgavies-Guthrie-Forfar-DD8-2TY-2-Bedroom-Detached-Bungalow-TSPC",
        "address": "Shadwell, Balgavies, Guthrie, Forfar DD8 2TY",
        "priceDescription": "Offers Over £215,000",
        "summary": "Detached Bungalow",
        "bedrooms": 2,
        "id": "645311e05a2ec8885beec97dab2a7770"
    },
    {
        "url": "https://www.sspc.co.uk/82-Bellevue-Gardens-Arbroath-DD11-5BQ-3-Bedroom-Detached-Bungalow-TSPC",
        "address": "82 Bellevue Gardens, Arbroath DD11 5BQ",
        "priceDescription": "Offers Over £215,000",
        "summary": "Detached Bungalow",
        "bedrooms": 3,
        "id": "70a3f023231cd59c4ecbd5c65f64ce4d"
    },
    {
        "url": "https://www.sspc.co.uk/67-Barry-Downs-Park-Barry-DD7-7SA-2-Bedroom-Detached-Bungalow-TSPC",
        "address": "67 Barry Downs Park, Barry DD7 7SA",
        "priceDescription": "Fixed £214,950",
        "summary": "Detached Bungalow",
        "bedrooms": 2,
        "id": "87539de2e956e341034631aa2c0b97ef"
    },
    {
        "url": "https://www.sspc.co.uk/3-Bennecourt-Crescent-COLDSTREAM-TD12-4BX-3-Bedroom-Detached-Bungalow-ESPC",
        "address": "3 Bennecourt Crescent, COLDSTREAM TD12 4BX",
        "priceDescription": "Offers over £210,000",
        "summary": "Detached Bungalow",
        "bedrooms": 3,
        "id": "857df82fb427877374bf82d6a55e1c82"
    },
    {
        "url": "https://www.sspc.co.uk/28-Trinity-Park-DUNS-TD11-3HN-2-Bedroom-Detached-Bungalow-ESPC",
        "address": "28 Trinity Park, DUNS TD11 3HN",
        "priceDescription": "Offers over £210,000",
        "summary": "Detached Bungalow",
        "bedrooms": 2,
        "id": "6f4e89b039766b99a0460280f2278730"
    },
    {
        "url": "https://www.sspc.co.uk/15-Schoolhill-Leuchars-ST.-ANDREWS-KY16-0EL-3-Bedroom-Terraced-Bungalow-ESPC",
        "address": "15 Schoolhill, Leuchars, ST. ANDREWS KY16 0EL",
        "priceDescription": "Offers over £210,000",
        "summary": "Terraced Bungalow",
        "bedrooms": 3,
        "id": "9164aa46b2e9baa5f5e555b8cd9ae12a"
    },
    {
        "url": "https://www.sspc.co.uk/50-Ethie-Terrace-Arbroath-DD11-4AB-2-Bedroom-Detached-Bungalow-TSPC",
        "address": "50 Ethie Terrace, Arbroath DD11 4AB",
        "priceDescription": "Offers Over £210,000",
        "summary": "Detached Bungalow",
        "bedrooms": 2,
        "id": "efa3957bb44a2eb01f36e97d0e5a0eac"
    },
    {
        "url": "https://www.sspc.co.uk/Kingarth-Cottage-Little-Brechin-Brechin-DD9-6RQ-3-Bedroom-Detached-Bungalow-TSPC",
        "address": "Kingarth Cottage, Little Brechin, Brechin DD9 6RQ",
        "priceDescription": "Offers Over £210,000",
        "summary": "Detached Bungalow",
        "bedrooms": 3,
        "id": "10aad689c6e8776f44c0e862136676e9"
    },
    {
        "url": "https://www.sspc.co.uk/74-Menzieshill-Road-Dundee-DD2-1PU-2-Bedroom-Detached-Bungalow-TSPC",
        "address": "74 Menzieshill Road, Dundee DD2 1PU",
        "priceDescription": "Fixed £205,000",
        "summary": "Detached Bungalow",
        "bedrooms": 2,
        "id": "09354a34cb1e1c3d8395e387b3eda60d"
    },
    {
        "url": "https://www.sspc.co.uk/Phase-2-Pitcrocknie-Village-Alyth-PH11-8JJ-2-Bedroom-Bungalow-PSPC",
        "address": "Phase 2, Pitcrocknie Village, Alyth PH11 8JJ",
        "priceDescription": "From £202,950",
        "summary": "Bungalow",
        "bedrooms": 2,
        "id": "4f3be06a19c9da689ab52d5e38a88d53"
    },
    {
        "url": "https://www.sspc.co.uk/36-Drummormie-Road-Cairneyhill-DUNFERMLINE-KY12-8RL-3-Bedroom-Detached-Bungalow-ESPC",
        "address": "36 Drummormie Road, Cairneyhill, DUNFERMLINE KY12 8RL",
        "priceDescription": "Offers over £200,000",
        "summary": "Detached Bungalow",
        "bedrooms": 3,
        "id": "d4190b455de0d748bb4df142b598e7e1"
    },
    {
        "url": "https://www.sspc.co.uk/Lynburn-Manse-Lane-Comrie-PH6-2DU-2-Bedroom-Detached-Bungalow-PSPC",
        "address": "Lynburn, Manse Lane, Comrie  PH6 2DU",
        "priceDescription": "Offers Over £200,000",
        "summary": "Detached Bungalow",
        "bedrooms": 2,
        "id": "3afe7001c743f9fe0a9284ea753f24ee"
    },
    {
        "url": "https://www.sspc.co.uk/14-Parkhill-Place-Northmuir-Kirriemuir-DD8-4TA-3-Bedroom-Detached-Bungalow-TSPC",
        "address": "14 Parkhill Place, Northmuir, Kirriemuir DD8 4TA",
        "priceDescription": "Fixed £200,000",
        "summary": "Detached Bungalow",
        "bedrooms": 3,
        "id": "7d66a1cd1c7f910d99cfa8fed6dac0a0"
    },
    {
        "url": "https://www.sspc.co.uk/8-Eastbank-Place-Longforgan-DD2-5EQ-2-Bedroom-Semi-Detached-Bungalow-TSPC",
        "address": "8 Eastbank Place, Longforgan DD2 5EQ",
        "priceDescription": "Offers Over £200,000",
        "summary": "Semi-Detached Bungalow",
        "bedrooms": 2,
        "id": "573476a52fd446fbaca448ea98bb7223"
    },
    {
        "url": "https://www.sspc.co.uk/7-Knowe-Mauchline-KA5-5BY-4-Bedroom-Detached-Bungalow-ESPC",
        "address": "7 Knowe, Mauchline KA5 5BY",
        "priceDescription": "Offers over £199,999",
        "summary": "Detached Bungalow",
        "bedrooms": 4,
        "id": "af16e1ff7c6e28128fee012d5274ad94"
    },
    {
        "url": "https://www.sspc.co.uk/73-Dryfe-Park-Lockerbie-DG11-2AD-4-Bedroom-Detached-Bungalow-ESPC",
        "address": "73 Dryfe Park, Lockerbie DG11 2AD",
        "priceDescription": "Offers over £199,995",
        "summary": "Detached Bungalow",
        "bedrooms": 4,
        "id": "531a438773119e946e576a52b238bae1"
    },
    {
        "url": "https://www.sspc.co.uk/28-Thimblehall-Drive-DUNFERMLINE-KY12-7RH-2-Bedroom-Detached-Bungalow-ESPC",
        "address": "28 Thimblehall Drive, DUNFERMLINE KY12 7RH",
        "priceDescription": "Offers in excess of £195,000",
        "summary": "Detached Bungalow",
        "bedrooms": 2,
        "id": "53bd81ef7ea2a333140be389df72ebec"
    },
    {
        "url": "https://www.sspc.co.uk/27-Raillies-Avenue-LARGS-KA30-8QY-2-Bedroom-Semi-Detached-Bungalow-ESPC",
        "address": "27 Raillies Avenue, LARGS KA30 8QY",
        "priceDescription": "Offers over £195,000",
        "summary": "Semi-Detached Bungalow",
        "bedrooms": 2,
        "id": "96ed529684031499aa5695f105ff1df1"
    },
    {
        "url": "https://www.sspc.co.uk/50-Thomson-Crescent-Prestonpans-EH32-0AU-2-Bedroom-Detached-Bungalow-ESPC",
        "address": "50 Thomson Crescent, Prestonpans EH32 0AU",
        "priceDescription": "Offers over £195,000",
        "summary": "Detached Bungalow",
        "bedrooms": 2,
        "id": "7f8415d1be2dfa530e3fb42bccfaccc4"
    },
    {
        "url": "https://www.sspc.co.uk/32-St.-Andrew-Drive-CASTLE-DOUGLAS-DG7-1EW-2-Bedroom-Detached-Bungalow-ESPC",
        "address": "32 St. Andrew Drive, CASTLE DOUGLAS DG7 1EW",
        "priceDescription": "Offers over £195,000",
        "summary": "Detached Bungalow",
        "bedrooms": 2,
        "id": "9c24e9ae0d6da89fc842baf645d788ac"
    },
    {
        "url": "https://www.sspc.co.uk/29-Grangehill-Drive-Monifieth-DD5-4RG-2-Bedroom-Semi-Detached-Bungalow-TSPC",
        "address": "29 Grangehill Drive, Monifieth DD5 4RG",
        "priceDescription": "Offers Over £195,000",
        "summary": "Semi-Detached Bungalow",
        "bedrooms": 2,
        "id": "38972844518f918fc82b0b8423942ffa"
    },
    {
        "url": "https://www.sspc.co.uk/16-South-Hermitage-Street-Newcastleton-TD9-0QN-2-Bedroom-Semi-Detached-Bungalow-ESPC",
        "address": "16 South Hermitage Street, Newcastleton TD9 0QN",
        "priceDescription": "Offers over £190,000",
        "summary": "Semi-Detached Bungalow",
        "bedrooms": 2,
        "id": "0f0f118fcf1bcc97049c623c9cba6548"
    },
    {
        "url": "https://www.sspc.co.uk/15-Westgate-Friockheim-DD11-4TX-2-Bedroom-End-Terrace-Bungalow-TSPC",
        "address": "15 Westgate, Friockheim DD11 4TX",
        "priceDescription": "Fixed £190,000",
        "summary": "End Terrace Bungalow",
        "bedrooms": 2,
        "id": "b290f31abfedf3c1d86bc13a8c4e7141"
    },
    {
        "url": "https://www.sspc.co.uk/6-Bruce-Grove-Pencaitland-EH34-5BN-3-Bedroom-Detached-Bungalow-ESPC",
        "address": "6 Bruce Grove, Pencaitland EH34 5BN",
        "priceDescription": "Offers over £189,000",
        "summary": "Detached Bungalow",
        "bedrooms": 3,
        "id": "5f5728a440c40048d972c86f14c62cb2"
    },
    {
        "url": "https://www.sspc.co.uk/12-Armadale-Road-Bathgate-EH47-0EX-3-Bedroom-Detached-Bungalow-ESPC",
        "address": "12 Armadale Road, Bathgate EH47 0EX",
        "priceDescription": "Offers over £189,000",
        "summary": "Detached Bungalow",
        "bedrooms": 3,
        "id": "523dad17e0ae8a8f3760143fe25a62a0"
    },
    {
        "url": "https://www.sspc.co.uk/69-South-Street-Forfar-DD8-2BS-3-Bedroom-Detached-Bungalow-TSPC",
        "address": "69 South Street, Forfar DD8 2BS",
        "priceDescription": "Around £189,000",
        "summary": "Detached Bungalow",
        "bedrooms": 3,
        "id": "4fd463c512e87a6ec22bd6828666b03e"
    },
    {
        "url": "https://www.sspc.co.uk/17-Hamilton-Avenue-ST.-ANDREWS-KY16-8EH-1-Bedroom-Terraced-Bungalow-ESPC",
        "address": "17 Hamilton Avenue, ST. ANDREWS KY16 8EH",
        "priceDescription": "Offers over £185,000",
        "summary": "Terraced Bungalow",
        "bedrooms": 1,
        "id": "12a4111e97309ca7286342987c683856"
    },
    {
        "url": "https://www.sspc.co.uk/9-David-Lawson-Gardens-Westmuir-Kirriemuir-DD8-5LS-3-Bedroom-Semi-Detached-Bungalow-TSPC",
        "address": "9 David Lawson Gardens, Westmuir Kirriemuir DD8 5LS",
        "priceDescription": "Offers Over £185,000",
        "summary": "Semi-Detached Bungalow",
        "bedrooms": 3,
        "id": "89b1939aead972455af950c9fd3bb643"
    },
    {
        "url": "https://www.sspc.co.uk/45-Watson-Place-DUNFERMLINE-KY12-0DT-2-Bedroom-Semi-Detached-Bungalow-ESPC",
        "address": "45 Watson Place, DUNFERMLINE KY12 0DT",
        "priceDescription": "Offers In The Region Of £180,000",
        "summary": "Semi-Detached Bungalow",
        "bedrooms": 2,
        "id": "01054537d21fb245b2bfff81202b3ebe"
    },
    {
        "url": "https://www.sspc.co.uk/74-Drakemyre-DALRY-KA24-5JH-2-Bedroom-Detached-Bungalow-ESPC",
        "address": "74 Drakemyre, DALRY KA24 5JH",
        "priceDescription": "Offers over £180,000",
        "summary": "Detached Bungalow",
        "bedrooms": 2,
        "id": "0cc6ae3f058dba063a9a1a2ac65559c2"
    },
    {
        "url": "https://www.sspc.co.uk/4-Raven-Hill-Lochmaben-Lockerbie-DG11-1QZ-3-Bedroom-Detached-Bungalow-ESPC",
        "address": "4 Raven Hill, Lochmaben, Lockerbie DG11 1QZ",
        "priceDescription": "Offers over £180,000",
        "summary": "Detached Bungalow",
        "bedrooms": 3,
        "id": "819fde2502299b03669ac3fa485542cf"
    },
    {
        "url": "https://www.sspc.co.uk/26-Abertay-Street-Broughty-Ferry-DD5-2NN-2-Bedroom-Semi-Detached-Bungalow-TSPC",
        "address": "26 Abertay Street, Broughty Ferry DD5 2NN",
        "priceDescription": "Offers Over £180,000",
        "summary": "Semi-Detached Bungalow",
        "bedrooms": 2,
        "id": "900b9367cf7043d7c4cca838d8e1cc18"
    },
    {
        "url": "https://www.sspc.co.uk/Briar-Cottage-Main-Road-St-Cyrus-Montrose-DD10-0BA-2-Bedroom-Detached-Bungalow-TSPC",
        "address": "Briar Cottage, Main Road, St Cyrus, Montrose DD10 0BA",
        "priceDescription": "Offers Over £180,000",
        "summary": "Detached Bungalow",
        "bedrooms": 2,
        "id": "9c77db3d79cac0571535bf239e2250d4"
    },
    {
        "url": "https://www.sspc.co.uk/2-West-Grange-Street-Monifieth-DD5-4LD-2-Bedroom-Detached-Bungalow-TSPC",
        "address": "2 West Grange Street, Monifieth DD5 4LD",
        "priceDescription": "Offers Over £180,000",
        "summary": "Detached Bungalow",
        "bedrooms": 2,
        "id": "bb4d3e9222b15320fb721f3dc10461ed"
    },
    {
        "url": "https://www.sspc.co.uk/2-Heron-Rise-Dundee-DD4-9DH-3-Bedroom-Linked-Bungalow-TSPC",
        "address": "2 Heron Rise, Dundee DD4 9DH",
        "priceDescription": "Offers Over £179,999",
        "summary": "Linked Bungalow",
        "bedrooms": 3,
        "id": "5ebfb83cc98efeda9e9b07b560a8ba6d"
    },
    {
        "url": "https://www.sspc.co.uk/29-Moor-Road-AYR-KA8-9EW-2-Bedroom-Semi-Detached-Bungalow-ESPC",
        "address": "29 Moor Road, AYR KA8 9EW",
        "priceDescription": "Offers over £179,900",
        "summary": "Semi-Detached Bungalow",
        "bedrooms": 2,
        "id": "002c1f4e9fcd39ec19da4a8c30832be8"
    },
    {
        "url": "https://www.sspc.co.uk/Sandoon-East-Den-Brae-Forfar-DD8-2PJ-3-Bedroom-Detached-Bungalow-TSPC",
        "address": "Sandoon, East Den Brae, Forfar DD8 2PJ",
        "priceDescription": "Offers Over £175,000",
        "summary": "Detached Bungalow",
        "bedrooms": 3,
        "id": "c5a966717a9b065ed753d5a448dc7004"
    },
    {
        "url": "https://www.sspc.co.uk/77-Grangehill-Drive-Monifieth-DD5-4RR-2-Bedroom-Detached-Bungalow-TSPC",
        "address": "77 Grangehill Drive, Monifieth DD5 4RR",
        "priceDescription": "Offers Over £175,000",
        "summary": "Detached Bungalow",
        "bedrooms": 2,
        "id": "fc25055f5a390e8d5de40e2e8a5e2ee2"
    },
    {
        "url": "https://www.sspc.co.uk/5-Trinity-Fields-Crescent-Brechin-DD9-6YF-3-Bedroom-Detached-Bungalow-TSPC",
        "address": "5 Trinity Fields Crescent, Brechin DD9 6YF",
        "priceDescription": "Offers Over £173,000",
        "summary": "Detached Bungalow",
        "bedrooms": 3,
        "id": "77d6227cf27f6217a543db3670853711"
    },
    {
        "url": "https://www.sspc.co.uk/2-Blackacre-Courance-LOCKERBIE-DG11-1TR-2-Bedroom-Semi-Detached-Bungalow-ESPC",
        "address": "2 Blackacre, Courance, LOCKERBIE DG11 1TR",
        "priceDescription": "Offers over £165,000",
        "summary": "Semi-Detached Bungalow",
        "bedrooms": 2,
        "id": "b9b96b5807338645a3a24a2bb724af2c"
    },
    {
        "url": "https://www.sspc.co.uk/19-Malcolm-Crescent-Monifieth-DD5-4RT-2-Bedroom-Semi-Detached-Bungalow-TSPC",
        "address": "19 Malcolm Crescent, Monifieth DD5 4RT",
        "priceDescription": "Offers Over £164,999",
        "summary": "Semi-Detached Bungalow",
        "bedrooms": 2,
        "id": "a7197bed2d210300265e6c618cbe5dc9"
    },
    {
        "url": "https://www.sspc.co.uk/59-Burdiehouse-Street-EDINBURGH-EH17-8HE-1-Bedroom-Terraced-Bungalow-ESPC",
        "address": "59 Burdiehouse Street, EDINBURGH EH17 8HE",
        "priceDescription": "Fixed Price £160,000",
        "summary": "Terraced Bungalow",
        "bedrooms": 1,
        "id": "522c8a363f37cad0f53bb6ffb496072c"
    },
    {
        "url": "https://www.sspc.co.uk/127-Dundee-Road-Forfar-DD8-1JD-2-Bedroom-Terraced-Bungalow-TSPC",
        "address": "127 Dundee Road, Forfar DD8 1JD",
        "priceDescription": "Offers Over £160,000",
        "summary": "Terraced Bungalow",
        "bedrooms": 2,
        "id": "c035636d6527e6ae492c59ed8ee7efb0"
    },
    {
        "url": "https://www.sspc.co.uk/16-William-Street-DALBEATTIE-DG5-4EN-2-Bedroom-Semi-Detached-Bungalow-ESPC",
        "address": "16 William Street, DALBEATTIE DG5 4EN",
        "priceDescription": "Offers over £155,000",
        "summary": "Semi-Detached Bungalow",
        "bedrooms": 2,
        "id": "a26345fc8f3cf4b98071a5e9f31b3529"
    },
    {
        "url": "https://www.sspc.co.uk/13-Balgove-Avenue-Gauldry-DD6-8SQ-2-Bedroom-Semi-Detached-Bungalow-TSPC",
        "address": "13 Balgove Avenue, Gauldry DD6 8SQ",
        "priceDescription": "Offers Over £150,000",
        "summary": "Semi-Detached Bungalow",
        "bedrooms": 2,
        "id": "a077929eccf315f6bd787182e315c3d5"
    },
    {
        "url": "https://www.sspc.co.uk/4-Montgomerie-Avenue-Dundee-DD4-7RB-3-Bedroom-Semi-Detached-Bungalow-TSPC",
        "address": "4 Montgomerie Avenue, Dundee DD4 7RB",
        "priceDescription": "Offers Over £150,000",
        "summary": "Semi-Detached Bungalow",
        "bedrooms": 3,
        "id": "23aeed3cd8dea81548edb2db2480925f"
    },
    {
        "url": "https://www.sspc.co.uk/7-Roman-Road-Westmuir-Kirriemuir-DD8-5LT-2-Bedroom-Semi-Detached-Bungalow-TSPC",
        "address": "7 Roman Road, Westmuir, Kirriemuir DD8 5LT",
        "priceDescription": "Offers Over £150,000",
        "summary": "Semi-Detached Bungalow",
        "bedrooms": 2,
        "id": "eaaa7e97e465358b39209b20c57fe185"
    },
    {
        "url": "https://www.sspc.co.uk/7-Greenhill-Holding-KILMARNOCK-KA2-0DX-2-Bedroom-Detached-Bungalow-ESPC",
        "address": "7 Greenhill Holding, KILMARNOCK KA2 0DX",
        "priceDescription": "Offers over £149,000",
        "summary": "Detached Bungalow",
        "bedrooms": 2,
        "id": "9632099b58e08ddf64eddd9747ed6200"
    },
    {
        "url": "https://www.sspc.co.uk/Ancrum-22-Pleasance-Avenue-Dumfries-DG2-7JL-2-Bedroom-Detached-Bungalow-ESPC",
        "address": "Ancrum, 22 Pleasance Avenue, Dumfries DG2 7JL",
        "priceDescription": "Offers over £145,000",
        "summary": "Detached Bungalow",
        "bedrooms": 2,
        "id": "64e08829609c434ee36da222a1522f78"
    },
    {
        "url": "https://www.sspc.co.uk/10-Kirkland-Court-DUMFRIES-DG1-4LN-2-Bedroom-Semi-Detached-Bungalow-ESPC",
        "address": "10 Kirkland Court, DUMFRIES DG1 4LN",
        "priceDescription": "Offers In The Region Of £145,000",
        "summary": "Semi-Detached Bungalow",
        "bedrooms": 2,
        "id": "6973bc1808f63dd83170842def212927"
    },
    {
        "url": "https://www.sspc.co.uk/108-Brechin-Road-Arbroath-DD11-1TA-3-Bedroom-Semi-Detached-Bungalow-TSPC",
        "address": "108 Brechin Road, Arbroath DD11 1TA",
        "priceDescription": "Offers Over £145,000",
        "summary": "Semi-Detached Bungalow",
        "bedrooms": 3,
        "id": "80cbe6323552f29f4174ce1b3a35485f"
    },
    {
        "url": "https://www.sspc.co.uk/17-Pearse-Street-Brechin-DD9-6JR-3-Bedroom-Detached-Bungalow-TSPC",
        "address": "17 Pearse Street, Brechin DD9 6JR",
        "priceDescription": "Offers Over £145,000",
        "summary": "Detached Bungalow",
        "bedrooms": 3,
        "id": "3a90cc7eb4f9247a57b7b80501907571"
    },
    {
        "url": "https://www.sspc.co.uk/19-Panmure-Street-Carnoustie-DD7-7ND-2-Bedroom-End-Terrace-Bungalow-TSPC",
        "address": "19 Panmure Street, Carnoustie DD7 7ND",
        "priceDescription": "Offers Over £140,000",
        "summary": "End Terrace Bungalow",
        "bedrooms": 2,
        "id": "5654759af8fe982c4290a4812eb99e65"
    },
    {
        "url": "https://www.sspc.co.uk/9-Lochy-Street-Blairgowrie-PH10-6DS-2-Bedroom-Semi-Detached-Bungalow-PSPC",
        "address": "9 Lochy Street, Blairgowrie PH10 6DS",
        "priceDescription": "Fixed £139,950",
        "summary": "Semi-Detached Bungalow",
        "bedrooms": 2,
        "id": "1ca6ca396e861b954d28a4ae105630b6"
    },
    {
        "url": "https://www.sspc.co.uk/7-East-Road-Lowthertown-ANNAN-DG12-6TD-2-Bedroom-Terraced-Bungalow-ESPC",
        "address": "7 East Road, Lowthertown, ANNAN DG12 6TD",
        "priceDescription": "Offers over £135,000",
        "summary": "Terraced Bungalow",
        "bedrooms": 2,
        "id": "edb3ecea02fdf8af6ede4cdeb3e8eef3"
    },
    {
        "url": "https://www.sspc.co.uk/Ty-Mawr-Square-Point-Castle-Douglas-DG7-2LL-2-Bedroom-Terraced-Bungalow-ESPC",
        "address": "Ty Mawr, Square Point, Castle Douglas DG7 2LL",
        "priceDescription": "Offers In The Region Of £135,000",
        "summary": "Terraced Bungalow",
        "bedrooms": 2,
        "id": "75807dd69f6b0573f364e3d1ad413da9"
    },
    {
        "url": "https://www.sspc.co.uk/23-Carlaverock-Close-Tranent-EH33-2PP-1-Bedroom-Terraced-Bungalow-ESPC",
        "address": "23 Carlaverock Close, Tranent EH33 2PP",
        "priceDescription": "Offers over £135,000",
        "summary": "Terraced Bungalow",
        "bedrooms": 1,
        "id": "864d21672642fa26104b2f6398c05d85"
    },
    {
        "url": "https://www.sspc.co.uk/3-Braemar-Avenue-DUMFRIES-DG1-3BQ-2-Bedroom-Detached-Bungalow-ESPC",
        "address": "3 Braemar Avenue, DUMFRIES DG1 3BQ",
        "priceDescription": "Offers over £130,000",
        "summary": "Detached Bungalow",
        "bedrooms": 2,
        "id": "101494673ad8d8a6efcef69d42d02bca"
    },
    {
        "url": "https://www.sspc.co.uk/Briar-Lodge-River-Tilt-Leisure-Park-Blair-Atholl-PH18-5TE-3-Bedroom-Detached-Bungalow-PSPC",
        "address": "Briar Lodge, River Tilt Leisure Park, Blair Atholl PH18 5TE",
        "priceDescription": "Fixed £130,000",
        "summary": "Detached Bungalow",
        "bedrooms": 3,
        "id": "d918f102ef9995e626a633eed008f44d"
    },
    {
        "url": "https://www.sspc.co.uk/73-New-Abbey-Road-DUMFRIES-DG2-7LA-2-Bedroom-Semi-Detached-Bungalow-ESPC",
        "address": "73 New Abbey Road, DUMFRIES DG2 7LA",
        "priceDescription": "Offers over £125,000",
        "summary": "Semi-Detached Bungalow",
        "bedrooms": 2,
        "id": "093007e5235147afac3c75919ffa8c12"
    },
    {
        "url": "https://www.sspc.co.uk/24-Albert-Crescent-Newport-on-Tay-DD6-8DT-1-Bedroom-Semi-Detached-Bungalow-TSPC",
        "address": "24 Albert Crescent, Newport-on-Tay DD6 8DT",
        "priceDescription": "Offers Over £125,000",
        "summary": "Semi-Detached Bungalow",
        "bedrooms": 1,
        "id": "35419dc98b5cb67b0fa809ccc4ef38de"
    },
    {
        "url": "https://www.sspc.co.uk/Lochan-SL3-River-Tilt-Park-Bridge-of-Tilt-PH18-5TE-2-Bedroom-Detached-Bungalow-PSPC",
        "address": "Lochan SL3, River Tilt Park, Bridge of Tilt PH18 5TE",
        "priceDescription": "Around £120,000",
        "summary": "Detached Bungalow",
        "bedrooms": 2,
        "id": "ff3ba5fed51a584cbe03badd042dbe24"
    },
    {
        "url": "https://www.sspc.co.uk/10A-Princes-Street-Monifieth-DD5-4AN-Bungalow-TSPC",
        "address": "10A Princes Street, Monifieth DD5 4AN",
        "priceDescription": "Offers Over £120,000",
        "summary": "Bungalow",
        "bedrooms": null,
        "id": "666e62d41ecb75682ddcbdba73ac5157"
    },
    {
        "url": "https://www.sspc.co.uk/21-Milton-Street-Monifieth-DD5-4QF-1-Bedroom-Terraced-Bungalow-TSPC",
        "address": "21 Milton Street, Monifieth DD5 4QF",
        "priceDescription": "Offers Over £115,000",
        "summary": "Terraced Bungalow",
        "bedrooms": 1,
        "id": "08bf8ba6aa5c361a814ad294e62831bd"
    },
    {
        "url": "https://www.sspc.co.uk/4-Lochty-Council-Houses-Brechin-DD9-6RZ-3-Bedroom-Semi-Detached-Bungalow-TSPC",
        "address": "4 Lochty Council Houses, Brechin DD9 6RZ",
        "priceDescription": "Offers Over £110,000",
        "summary": "Semi-Detached Bungalow",
        "bedrooms": 3,
        "id": "04642ab71f968a724fc7ea27b48ebc49"
    },
    {
        "url": "https://www.sspc.co.uk/2-Westfield-Gardens-LOCKERBIE-DG11-2FB-2-Bedroom-Semi-Detached-Bungalow-ESPC",
        "address": "2 Westfield Gardens, LOCKERBIE DG11 2FB",
        "priceDescription": "Guide Price £105,000",
        "summary": "Semi-Detached Bungalow",
        "bedrooms": 2,
        "id": "c7fc081da53dd2fc2f6f05f334bd0459"
    },
    {
        "url": "https://www.sspc.co.uk/9-Myrtlehall-Gardens-Dundee-DD4-0TP-1-Bedroom-Semi-Detached-Bungalow-TSPC",
        "address": "9 Myrtlehall Gardens, Dundee DD4 0TP",
        "priceDescription": "Offers Over £105,000",
        "summary": "Semi-Detached Bungalow",
        "bedrooms": 1,
        "id": "c61ce5bccd61f5b10f8eb51353b58876"
    },
    {
        "url": "https://www.sspc.co.uk/8-Parkneuk-Road-DUNFERMLINE-KY12-9BL-1-Bedroom-Semi-Detached-Bungalow-ESPC",
        "address": "8 Parkneuk Road, DUNFERMLINE KY12 9BL",
        "priceDescription": "Offers over £100,000",
        "summary": "Semi-Detached Bungalow",
        "bedrooms": 1,
        "id": "3c1c7fef8042863187cd26a014872687"
    },
    {
        "url": "https://www.sspc.co.uk/Beinn-a'Ghlo-Lodge-River-Tilt-Park-Bridge-of-Tilt-PH18-5TE-2-Bedroom-Bungalow-PSPC",
        "address": "Beinn a'Ghlo Lodge, River Tilt Park, Bridge of Tilt PH18 5TE",
        "priceDescription": "Around £100,000",
        "summary": "Bungalow",
        "bedrooms": 2,
        "id": "bfb91e4c911e60bbb0c58819c9e5d4ea"
    },
    {
        "url": "https://www.sspc.co.uk/32-Prior-Road-Forfar-DD8-3DQ-1-Bedroom-Terraced-Bungalow-TSPC",
        "address": "32 Prior Road, Forfar DD8 3DQ",
        "priceDescription": "Fixed £92,000",
        "summary": "Terraced Bungalow",
        "bedrooms": 1,
        "id": "066b92107cad5d6721458e6cf38d77db"
    },
    {
        "url": "https://www.sspc.co.uk/Partridge-Lodge-River-Tilt-Park-Bridge-of-Tilt-PH18-5TE-2-Bedroom-Detached-Bungalow-PSPC",
        "address": "Partridge Lodge, River Tilt Park, Bridge of Tilt PH18 5TE",
        "priceDescription": "Offers Over £90,000",
        "summary": "Detached Bungalow",
        "bedrooms": 2,
        "id": "270abff87096d8f008cd12202ef425a3"
    },
    {
        "url": "https://www.sspc.co.uk/Pippin-Cottage-8-Rockhall-Road-Hightae-LOCKERBIE-DG11-1JP-2-Bedroom-Detached-Bungalow-ESPC",
        "address": "Pippin Cottage, 8 Rockhall Road, Hightae, LOCKERBIE DG11 1JP",
        "priceDescription": "Offers over £80,000",
        "summary": "Detached Bungalow",
        "bedrooms": 2,
        "id": "c8825f564f59a5c898f6c552a18eb13a"
    },
    {
        "url": "https://www.sspc.co.uk/1-Park-Village-Turretbank-Road-Crieff-PH7-4JN-2-Bedroom-Detached-Bungalow-PSPC",
        "address": "1 Park Village, Turretbank Road, Crieff PH7 4JN",
        "priceDescription": "Offers Over £80,000",
        "summary": "Detached Bungalow",
        "bedrooms": 2,
        "id": "50d960ab84418d3cfe007a53bee67080"
    },
    {
        "url": "https://www.sspc.co.uk/The-Smiddy-Chapelton-Arbroath-DD11-4RT-Detached-Bungalow-TSPC",
        "address": "The Smiddy, Chapelton, Arbroath DD11 4RT",
        "priceDescription": "Offers Over £75,000",
        "summary": "Detached Bungalow",
        "bedrooms": null,
        "id": "6ce04cb986db6486719c3468c1794d2d"
    },
    {
        "url": "https://www.sspc.co.uk/13-East-Sunnyside-Forfar-DD8-1DZ-1-Bedroom-Terraced-Bungalow-TSPC",
        "address": "13 East Sunnyside, Forfar DD8 1DZ",
        "priceDescription": "Offers Over £75,000",
        "summary": "Terraced Bungalow",
        "bedrooms": 1,
        "id": "ef10f3c6351dba8be26007e1faaef19f"
    },
    {
        "url": "https://www.sspc.co.uk/11c-Scott-Street-Brechin-DD9-7BQ-2-Bedroom-Semi-Detached-Bungalow-TSPC",
        "address": "11c Scott Street, Brechin DD9 7BQ",
        "priceDescription": "Offers Over £65,000",
        "summary": "Semi-Detached Bungalow",
        "bedrooms": 2,
        "id": "236d2d6fdb9e9bde7bb6b73a9700d764"
    },
    {
        "url": "https://www.sspc.co.uk/43-Helena-Place-Kirn-PA23-8HF-1-Bedroom-Semi-Detached-Bungalow-ESPC",
        "address": "43 Helena Place, Kirn PA23 8HF",
        "priceDescription": "Offers over £55,000",
        "summary": "Semi-Detached Bungalow",
        "bedrooms": 1,
        "id": "1064e0d93ca9ac4c757c7785c7d91ed2"
    },
    {
        "url": "https://www.sspc.co.uk/Rannoch-35-Lochlands-Leisure-Park-Dundee-Road-Forfar-DD8-1XF-2-Bedroom-Detached-Bungalow-TSPC",
        "address": "Rannoch, 35 Lochlands Leisure Park Dundee Road, Forfar DD8 1XF",
        "priceDescription": "Fixed £54,000",
        "summary": "Detached Bungalow",
        "bedrooms": 2,
        "id": "09cdefdde4c2b554f0ce03a79e46e9fe"
    }
]